valicoc/__init__.py
valicoc/__main__.py
valicoc/core.py
ValiCoC-999.99.9.post1.dist-info/METADATA
ValiCoC-999.99.9.post1.dist-info/WHEEL
ValiCoC-999.99.9.post1.dist-info/top_level.txt
ValiCoC-999.99.9.post1.dist-info/RECORD
