Metadata-Version: 2.1
Name: ValiCoC
Version: 999.99.9.post1
Summary: Validation code filter
Home-page: https://github.com/Adam-Miao/ValiCoC/
Author: O_O
Author-email: Adammiao@outlook.com
License: UNKNOWN
Platform: UNKNOWN
Classifier: Programming Language :: Python :: 3
